{
  "ancestry": "elf",
  "description": "Elven names are elegant and flowing, often with nature themes",
  "hasLastNames": true,
  "structures": [
    { "type": "syllabic", "weight": 70 },
    { "type": "first-last", "weight": 30 }
  ],
  "lengthWeights": {
    "2": 50,
    "3": 50
  },
  "male": {
    "prefixes": ["Ael", "Aer", "Alf", "Alt", "Amar", "Ang", "Ara", "Aren", "Ari", "Arun", "Bael", "Ber", "Bor", "Bran", "Cal", "Calan", "Carath", "Cel", "Cor", "Cyran", "Dael", "Dal", "Dar", "Del", "Dor", "Dral", "El", "Elar", "Eld", "Elen", "Eli", "Elion", "Elr", "Elth", "Eol", "Er", "Eran", "Eron", "Eth", "Evan", "Fael", "Faran", "Farl", "Fel", "Fen", "Fin", "Gael", "Gal", "Galan", "Gar", "Gil", "Glar", "Glor", "Hal", "Harad", "Hel", "Helio", "Hor", "Il", "Ilan", "Ilen", "Ilmar", "Imr", "Ior", "Ith", "Ivar", "Jor", "Kal", "Kalen", "Kar", "Kel", "Kyr", "Lael", "Lae", "Laer", "Lath", "Legol", "Lir", "Lor", "Loren", "Mel", "Mir", "Mor", "Nal", "Nar", "Nim", "Nor", "Olor", "Orel", "Oren", "Oril", "Pel", "Phaer", "Rel", "Ren", "Rhy", "Sal", "Sel", "Sil", "Sol", "Tar", "Thal", "Thar", "Thel", "Thor", "Tir", "Tor", "Var", "Vel", "Vor", "Xan", "Yel", "Yor", "Zor"],
    "middles": ["ad", "al", "an", "ar", "ath", "dir", "dor", "drin", "el", "en", "er", "eron", "eth", "ian", "il", "in", "ion", "ir", "ith", "lan", "las", "lin", "mir", "mon", "nal", "nath", "nel", "nin", "oln", "on", "or", "ran", "ras", "ryn", "thal", "thas", "thil", "van", "ven", "vol", "wen"],
    "suffixes": ["ac", "adan", "adil", "adir", "alas", "alath", "amar", "an", "andar", "ar", "aran", "aras", "as", "ath", "athas", "bor", "dan", "dar", "dir", "dor", "dras", "duil", "el", "elan", "emar", "en", "endil", "enil", "eth", "il", "ion", "ionel", "las", "lath", "lin", "lon", "mir", "mon", "nath", "ndil", "nil", "on", "ondil", "or", "oril", "ran", "rath", "rian", "riel", "ron", "ros", "sil", "than", "thar", "thil", "thir", "thras", "ven", "wen", "wil", "wyn"]
  },
  "female": {
    "prefixes": ["Ael", "Aela", "Aer", "Aera", "Al", "Ala", "Amar", "Ara", "Ari", "Arin", "Arwen", "Cael", "Caela", "Cal", "Cara", "Cel", "Cela", "Celi", "Cor", "Cyra", "Dael", "Daer", "Del", "Dela", "El", "Ela", "Elar", "Eli", "Elin", "Ella", "Elora", "Elwyn", "Elysia", "Eth", "Fae", "Fael", "Faela", "Feli", "Fin", "Fira", "Gael", "Gala", "Gali", "Gil", "Gwel", "Gwenn", "Hal", "Hala", "Il", "Ila", "Ilen", "Ilis", "Ilph", "Ilya", "Imral", "Ire", "Isa", "Isel", "Jael", "Jela", "Kal", "Kael", "Kel", "Kela", "Lae", "Laer", "Lara", "Lau", "Leth", "Lira", "Lis", "Lor", "Lora", "Lyra", "Mae", "Mel", "Mela", "Mer", "Mera", "Mira", "Myria", "Myri", "Nael", "Nal", "Nara", "Nel", "Nia", "Nim", "Nor", "Nora", "Ola", "Ora", "Orel", "Ori", "Phae", "Phaela", "Quen", "Rael", "Rae", "Rin", "Ryla", "Sael", "Sae", "Sel", "Sera", "Syl", "Syra", "Tael", "Tara", "Tel", "Thae", "Thal", "Tira", "Tyl", "Val", "Vara", "Vel", "Vyra", "Wen", "Xae", "Yel", "Yra", "Zae", "Zara"],
    "middles": ["an", "ar", "ara", "ath", "el", "ela", "en", "enn", "eth", "ia", "ian", "il", "ila", "in", "ina", "ir", "ira", "is", "ith", "la", "lan", "las", "len", "lin", "lith", "lyn", "mia", "na", "nath", "nel", "nia", "ra", "rae", "ren", "ria", "ril", "rin", "ris", "sil", "tha", "thal", "va", "ven", "via", "wen", "win", "wyn", "ya", "yn"],
    "suffixes": ["a", "ae", "ael", "aen", "aer", "ala", "alis", "ana", "andra", "ara", "arel", "aria", "as", "ath", "aya", "bel", "bella", "dia", "dra", "driel", "el", "ela", "ella", "elyn", "en", "ena", "enna", "eria", "es", "eth", "eya", "ia", "iel", "ila", "ilis", "in", "ina", "ira", "ira", "is", "isa", "ith", "la", "lia", "lin", "lis", "lith", "lyn", "mia", "mira", "na", "nia", "nna", "ora", "ra", "rae", "ria", "riel", "rin", "ris", "sia", "ssiel", "thal", "thil", "va", "via", "wen", "win", "wyn", "ya", "yna", "yra", "ys"]
  },
  "nonbinary": {
    "prefixes": ["Ael", "Aer", "Al", "Ara", "Ari", "Bael", "Cal", "Cael", "Cel", "Cyra", "Dael", "Dal", "Del", "El", "Ela", "Eli", "Er", "Eth", "Fael", "Fae", "Fel", "Fin", "Gael", "Gal", "Gil", "Gwel", "Hal", "Hala", "Il", "Ila", "Ilen", "Imr", "Ior", "Isel", "Ith", "Jael", "Kal", "Kael", "Kel", "Kyr", "Lae", "Laer", "Lara", "Legol", "Leth", "Lir", "Lor", "Lyra", "Mae", "Mel", "Mir", "Myri", "Nael", "Nal", "Nara", "Nel", "Nim", "Nor", "Nora", "Olor", "Ora", "Orel", "Ori", "Oren", "Pel", "Phae", "Phaer", "Quen", "Rael", "Rae", "Rel", "Ren", "Rhy", "Rin", "Ryla", "Sael", "Sae", "Sel", "Sera", "Sil", "Sol", "Syl", "Syra", "Tael", "Tar", "Thal", "Thar", "Thel", "Tir", "Tyl", "Val", "Var", "Vel", "Vor", "Vyra", "Wen", "Xae", "Xan", "Yel", "Yra", "Zae", "Zara", "Zor"],
    "middles": ["ad", "al", "an", "ar", "ara", "ath", "dir", "el", "ela", "en", "er", "eth", "ia", "ian", "il", "in", "ion", "ir", "ira", "is", "ith", "la", "lan", "las", "lin", "lyn", "mir", "na", "nath", "nel", "nin", "on", "or", "ra", "ran", "ren", "ria", "ril", "rin", "thal", "tha", "van", "ven", "wen", "wyn", "yn"],
    "suffixes": ["a", "ac", "adan", "ael", "aen", "alas", "an", "ana", "andar", "ar", "ara", "aran", "as", "ath", "dan", "dil", "dir", "dor", "el", "ela", "ella", "en", "endil", "enna", "eth", "eya", "ia", "iel", "il", "ila", "in", "ina", "ion", "ionel", "ir", "ira", "is", "ith", "la", "lan", "las", "lin", "lis", "lon", "lyn", "mir", "na", "nath", "ndil", "nia", "on", "ondil", "or", "ora", "ra", "rae", "rian", "riel", "rin", "ris", "ron", "sil", "tha", "thal", "than", "thil", "va", "ven", "wen", "win", "wyn", "ya", "yn", "yra"]
  },
  "lastNames": ["Autumnleaf", "Brightwood", "Dawnwhisper", "Evergreen", "Moonbrook", "Nightwind", "Silverstream", "Starlight", "Sunblade", "Willowshade"],
  "lastNamePrefixes": ["Amber", "Autumn", "Azure", "Bright", "Crystal", "Dawn", "Diamond", "Dusk", "Ever", "Fair", "Forest", "Frost", "Golden", "Green", "Light", "Lunar", "Mist", "Moon", "Morning", "Night", "Pearl", "Rain", "River", "Rose", "Shadow", "Silver", "Sky", "Snow", "Solar", "Spring", "Star", "Storm", "Summer", "Sun", "Thorn", "Thunder", "Twilight", "Whisper", "Wild", "Willow", "Wind", "Winter", "Wood"],
  "lastNameSuffixes": ["arrow", "bark", "blossom", "bloom", "blade", "branch", "breeze", "brook", "caller", "dancer", "dream", "fall", "feather", "flame", "glade", "grace", "grove", "heart", "keeper", "leaf", "light", "moon", "petal", "rain", "river", "runner", "shade", "shadow", "shield", "singer", "song", "spear", "spirit", "star", "stone", "stream", "sun", "thorn", "walker", "warden", "whisper", "wind", "wing", "wood"]
}
